{"@context":"http://iiif.io/api/presentation/3/context.json","id":"https://test.iiif.library.ucla.edu/collections/ark%3A%2F21198%2Fz1545zvh","type":"Collection","label":{"none":["Qiu ming ji : [er juan / Hu Ying zhu] | 秋鳴集 : [二卷 / 胡瑩著]"]},"behavior":["multi-part"],"metadata":[{"label":{"none":["Rights contact"]},"value":{"none":["https://www.library.ucla.edu/location/east-asian-library-richard-c-rudolph; 310-825-1401"]}}],"items":[{"id":"https://test.iiif.library.ucla.edu/ark%3A%2F21198%2Fz1865s2r/manifest","type":"Manifest","label":{"none":["Vol. 1"]}},{"id":"https://test.iiif.library.ucla.edu/ark%3A%2F21198%2Fz14f51bd/manifest","type":"Manifest","label":{"none":["Vol. 2"]}}]}